<?xml version="1.0" encoding="utf-8"?><Regulation gazette-part="II" regulation-type="SOR" xml:lang="fr" startdate="20070315"><Identification Code="id=&quot;&quot;"><LimsAuthority><Alpha>P-33.01</Alpha><AuthorityTitle>Loi sur l’emploi dans la fonction publique</AuthorityTitle></LimsAuthority><InstrumentNumber>DORS/2007-54</InstrumentNumber><RegistrationDate><Date><YYYY>2007</YYYY><MM>3</MM><DD>15</DD></Date></RegistrationDate><ConsolidationDate><Date><YYYY>2013</YYYY><MM>01</MM><DD>28</DD></Date></ConsolidationDate><LastModifiedDate><Date><YYYY>2007</YYYY><MM>4</MM><DD>5</DD></Date></LastModifiedDate><EnablingAuthority Code="id=&quot;&quot;,ea=&quot;&quot;"><XRefExternal reference-type="act">LOI SUR L’EMPLOI DANS LA FONCTION PUBLIQUE</XRefExternal></EnablingAuthority><LongTitle Code="id=&quot;&quot;,lt=&quot;&quot;">Modalités d’emploi du ombudsman fédéral des victimes d’actes criminels</LongTitle><RegulationMakerOrder><RegulationMaker>C.P.</RegulationMaker><OrderNumber>2007-355</OrderNumber><Date><YYYY>2007</YYYY><MM>3</MM><DD>15</DD></Date></RegulationMakerOrder></Identification><Order Code="od=&quot;&quot;"><Provision format-ref="indent-1-0" language-align="yes" Code="od=&quot;&quot;,pv=&quot;&quot;,nb=&quot;1&quot;"><Text>Attendu que, en vertu de l’alinéa 127.1(1)<Emphasis style="italic">c</Emphasis>) de la <XRefExternal reference-type="act" link="P-33.01">Loi sur l’emploi dans la fonction publique</XRefExternal>, le gouverneur en conseil peut nommer un conseiller spécial d’un ministre;</Text></Provision><Provision format-ref="indent-1-0" Code="od=&quot;&quot;,pv=&quot;&quot;,nb=&quot;2&quot;"><Text>Attendu que la gouverneure en conseil juge nécessaire qu’il y ait un conseiller spécial du ministre de la Justice agissant comme ombudsman fédéral des victimes d’actes criminels,</Text></Provision><Provision format-ref="indent-1-0" Code="od=&quot;&quot;,pv=&quot;&quot;,nb=&quot;3&quot;"><Text>À ces causes, sur recommandation du premier ministre, Son Excellence la Gouverneure générale en conseil établit, conformément à l’annexe ci-jointe, les modalités d’emploi du conseiller spécial du ministre de la Justice, lequel doit porter le titre d’ombudsman fédéral des victimes d’actes criminels, que le gouverneur en conseil peut nommer en vertu de l’alinéa 127.1(1)<Emphasis style="italic">c</Emphasis>) de la <XRefExternal reference-type="act" link="P-33.01">Loi sur l’emploi dans la fonction publique</XRefExternal>.</Text></Provision></Order><Schedule Code="sc=&quot;&quot;,nb=&quot;1&quot;"><ScheduleFormHeading Code="sc=&quot;&quot;,nb=&quot;1&quot;,sf=&quot;&quot;"><Label>ANNEXE</Label></ScheduleFormHeading><RegulationPiece><Body><Group1-Part Code="sc=&quot;&quot;,nb=&quot;1&quot;,ga=&quot;s_1&quot;"><Heading Code="sc=&quot;&quot;,nb=&quot;1&quot;,ga=&quot;s_1&quot;,h1=&quot;&quot;"><TitleText Code="sc=&quot;&quot;,nb=&quot;1&quot;,ga=&quot;s_1&quot;,h1=&quot;&quot;,t1=&quot;&quot;,nb=&quot;1&quot;">INTERPRÉTATION</TitleText></Heading><Section Code="sc=&quot;&quot;,nb=&quot;1&quot;,ga=&quot;s_1&quot;,se=&quot;1&quot;"><Label>1.</Label><Text>Dans la présente annexe, <DefinedTermFr>victime</DefinedTermFr> s’entend de ce qui suit :</Text><Paragraph Code="sc=&quot;&quot;,nb=&quot;1&quot;,ga=&quot;s_1&quot;,se=&quot;1&quot;,p1=&quot;a&quot;"><Label><Emphasis style="italic">a</Emphasis>)</Label><Text>toute personne qui a subi des pertes ou des dommages — matériels, corporels ou moraux — par suite de la perpétration d’une infraction criminelle au Canada. Est assimilée à la victime, si celle-ci est décédée, malade ou incapable de faire valoir ses droits, son époux ou conjoint de fait, un parent, quiconque en a la garde en droit ou en fait, toute personne aux soins de laquelle elle est confiée ou qui est chargée de son entretien, ou toute personne à sa charge;</Text></Paragraph><Paragraph Code="sc=&quot;&quot;,nb=&quot;1&quot;,ga=&quot;s_1&quot;,se=&quot;1&quot;,p1=&quot;b&quot;"><Label><Emphasis style="italic">b</Emphasis>)</Label><Text>à l’égard des droits des victimes prévus par la <XRefExternal reference-type="act" link="C-44.6">Loi sur le système correctionnel et la mise en liberté sous condition</XRefExternal>, toute victime au sens du paragraphe 2(1) de cette loi ou toute personne dont le Commissaire du service correctionel du Canada conclut qu’elle répond aux critères établis aux paragraphes 26(3) ou (4) de cette loi ou dont le président de la Commission nationale des libérations conditionnelles conclut qu’elle répond aux critères établis au paragraphe 142(3) de la même loi.</Text></Paragraph></Section></Group1-Part><Group1-Part Code="sc=&quot;&quot;,nb=&quot;1&quot;,ga=&quot;s_2&quot;"><Heading Code="sc=&quot;&quot;,nb=&quot;1&quot;,ga=&quot;s_2&quot;,h1=&quot;&quot;"><TitleText Code="sc=&quot;&quot;,nb=&quot;1&quot;,ga=&quot;s_2&quot;,h1=&quot;&quot;,t1=&quot;&quot;,nb=&quot;2&quot;">NOMINATION</TitleText></Heading><Section Code="sc=&quot;&quot;,nb=&quot;1&quot;,ga=&quot;s_2&quot;,se=&quot;2&quot;"><Label>2.</Label><Text>L’ombudsman fédéral des victimes d’actes criminels (« ombudsman ») est nommé par le gouverneur en conseil pour un mandat renouvelable de trois ans, sauf révocation motivée de la part du gouverneur en conseil.</Text></Section></Group1-Part><Group1-Part Code="sc=&quot;&quot;,nb=&quot;1&quot;,ga=&quot;s_3&quot;"><Heading Code="sc=&quot;&quot;,nb=&quot;1&quot;,ga=&quot;s_3&quot;,h1=&quot;&quot;"><TitleText Code="sc=&quot;&quot;,nb=&quot;1&quot;,ga=&quot;s_3&quot;,h1=&quot;&quot;,t1=&quot;&quot;,nb=&quot;3&quot;">PERSONNEL</TitleText></Heading><Section Code="sc=&quot;&quot;,nb=&quot;1&quot;,ga=&quot;s_3&quot;,se=&quot;3&quot;"><Label>3.</Label><Text>Le personnel du Bureau de l’ombudsman fédéral des victimes d’actes criminels est embauché conformément à la <XRefExternal reference-type="act" link="P-33.01">Loi sur l’emploi dans la fonction publique</XRefExternal> et fait partie du ministère de la Justice.</Text></Section></Group1-Part><Group1-Part Code="sc=&quot;&quot;,nb=&quot;1&quot;,ga=&quot;s_4&quot;"><Heading Code="sc=&quot;&quot;,nb=&quot;1&quot;,ga=&quot;s_4&quot;,h1=&quot;&quot;"><TitleText Code="sc=&quot;&quot;,nb=&quot;1&quot;,ga=&quot;s_4&quot;,h1=&quot;&quot;,t1=&quot;&quot;,nb=&quot;4&quot;">MANDAT</TitleText></Heading><Section Code="sc=&quot;&quot;,nb=&quot;1&quot;,ga=&quot;s_4&quot;,se=&quot;4&quot;"><Label>4.</Label><Subsection Code="sc=&quot;&quot;,nb=&quot;1&quot;,ga=&quot;s_4&quot;,se=&quot;4&quot;,ss=&quot;1&quot;"><Label>(1)</Label><Text>Le mandat de l’ombudsman porte exclusivement sur des questions de compétence fédérale.</Text></Subsection><Subsection Code="sc=&quot;&quot;,nb=&quot;1&quot;,ga=&quot;s_4&quot;,se=&quot;4&quot;,ss=&quot;2&quot;"><Label>(2)</Label><Text>L’ombudsman a pour mandat :</Text><Paragraph Code="sc=&quot;&quot;,nb=&quot;1&quot;,ga=&quot;s_4&quot;,se=&quot;4&quot;,ss=&quot;2&quot;,p1=&quot;a&quot;"><Label><Emphasis style="italic">a</Emphasis>)</Label><Text>de promouvoir pour les victimes l’accès aux programmes et aux services fédéraux existants à leur intention;</Text></Paragraph><Paragraph Code="sc=&quot;&quot;,nb=&quot;1&quot;,ga=&quot;s_4&quot;,se=&quot;4&quot;,ss=&quot;2&quot;,p1=&quot;b&quot;"><Label><Emphasis style="italic">b</Emphasis>)</Label><Text>de répondre aux plaintes provenant de victimes à l’égard du non-respect des dispositions de la <XRefExternal reference-type="act" link="C-44.6">Loi sur le système correctionnel et la mise en liberté sous condition</XRefExternal> qui s’appliquent aux victimes d’actes criminels perpétrés par des délinquants relevant des autorités fédérales;</Text></Paragraph><Paragraph Code="sc=&quot;&quot;,nb=&quot;1&quot;,ga=&quot;s_4&quot;,se=&quot;4&quot;,ss=&quot;2&quot;,p1=&quot;c&quot;"><Label><Emphasis style="italic">c</Emphasis>)</Label><Text>de faire connaître au personnel du système de justice pénale et aux responsables des orientations politiques les besoins et les préoccupations des victimes d’actes criminels, ainsi que les lois qui les défendent, et, notamment, de promouvoir les principes énoncés dans la <XRefExternal reference-type="other">Déclaration canadienne des principes fondamentaux de justice relatifs aux victimes de la criminalité</XRefExternal> dans les domaines de compétence fédérale;</Text></Paragraph><Paragraph Code="sc=&quot;&quot;,nb=&quot;1&quot;,ga=&quot;s_4&quot;,se=&quot;4&quot;,ss=&quot;2&quot;,p1=&quot;d&quot;"><Label><Emphasis style="italic">d</Emphasis>)</Label><Text>de cerner et d’examiner les nouveaux enjeux et les problèmes systémiques, y compris ceux – reliés aux programmes et services offerts ou administrés par le ministère de la Justice ou le ministère de la Securité publique et de la Protection civile – qui ont une incidence négative sur les victimes d’actes criminels;</Text></Paragraph><Paragraph Code="sc=&quot;&quot;,nb=&quot;1&quot;,ga=&quot;s_4&quot;,se=&quot;4&quot;,ss=&quot;2&quot;,p1=&quot;e&quot;"><Label><Emphasis style="italic">e</Emphasis>)</Label><Text>de faciliter pour les victimes l’accès aux programmes et aux services fédéraux existants en leur fournissant de l’information et des services d’aiguillage.</Text></Paragraph></Subsection></Section></Group1-Part><Group1-Part Code="sc=&quot;&quot;,nb=&quot;1&quot;,ga=&quot;s_5&quot;"><Heading Code="sc=&quot;&quot;,nb=&quot;1&quot;,ga=&quot;s_5&quot;,h1=&quot;&quot;"><TitleText Code="sc=&quot;&quot;,nb=&quot;1&quot;,ga=&quot;s_5&quot;,h1=&quot;&quot;,t1=&quot;&quot;,nb=&quot;5&quot;">LIMITES DU MANDAT</TitleText></Heading><Section Code="sc=&quot;&quot;,nb=&quot;1&quot;,ga=&quot;s_5&quot;,se=&quot;5&quot;"><Label>5.</Label><Subsection Code="sc=&quot;&quot;,nb=&quot;1&quot;,ga=&quot;s_5&quot;,se=&quot;5&quot;,ss=&quot;1&quot;"><Label>(1)</Label><Text>L’examen de l’ombudsman ne peut porter sur des faits survenus avant la date de la création de son Bureau, si ce n’est à la demande du ministre de la Justice ou du ministre de la Sécurité publique et de la Protection civile.</Text></Subsection><Subsection Code="sc=&quot;&quot;,nb=&quot;1&quot;,ga=&quot;s_5&quot;,se=&quot;5&quot;,ss=&quot;2&quot;"><Label>(2)</Label><Text>L’ombudsman ne peut examiner :</Text><Paragraph Code="sc=&quot;&quot;,nb=&quot;1&quot;,ga=&quot;s_5&quot;,se=&quot;5&quot;,ss=&quot;2&quot;,p1=&quot;a&quot;"><Label><Emphasis style="italic">a</Emphasis>)</Label><Text>les recommandations formulées par le Service correctionnel du Canada à la Commission nationale des libérations conditionnelles ou à toute commission provinciale des libérations conditionnelles;</Text></Paragraph><Paragraph Code="sc=&quot;&quot;,nb=&quot;1&quot;,ga=&quot;s_5&quot;,se=&quot;5&quot;,ss=&quot;2&quot;,p1=&quot;b&quot;"><Label><Emphasis style="italic">b</Emphasis>)</Label><Text>les décisions de la Commission nationale des libérations conditionnelles ou de toute commission provinciale des libérations conditionnelles;</Text></Paragraph><Paragraph Code="sc=&quot;&quot;,nb=&quot;1&quot;,ga=&quot;s_5&quot;,se=&quot;5&quot;,ss=&quot;2&quot;,p1=&quot;c&quot;"><Label><Emphasis style="italic">c</Emphasis>)</Label><Text>les décisions du Service correctionel du Canada concernant le transfert de détenus à un autre pénitencier ou les autorisations, notamment les placements à l’extérieur et les permissions de sortir avec ou sans escorte;</Text></Paragraph><Paragraph Code="sc=&quot;&quot;,nb=&quot;1&quot;,ga=&quot;s_5&quot;,se=&quot;5&quot;,ss=&quot;2&quot;,p1=&quot;d&quot;"><Label><Emphasis style="italic">d</Emphasis>)</Label><Text>les décisions judiciaires, ainsi que les décisions des juges ou juges de paix;</Text></Paragraph><Paragraph Code="sc=&quot;&quot;,nb=&quot;1&quot;,ga=&quot;s_5&quot;,se=&quot;5&quot;,ss=&quot;2&quot;,p1=&quot;e&quot;"><Label><Emphasis style="italic">e</Emphasis>)</Label><Text>les décisions d’intenter ou non des poursuites;</Text></Paragraph><Paragraph Code="sc=&quot;&quot;,nb=&quot;1&quot;,ga=&quot;s_5&quot;,se=&quot;5&quot;,ss=&quot;2&quot;,p1=&quot;f&quot;"><Label><Emphasis style="italic">f</Emphasis>)</Label><Text>les documents confidentiels du Conseil privé de la Reine pour le Canada;</Text></Paragraph><Paragraph Code="sc=&quot;&quot;,nb=&quot;1&quot;,ga=&quot;s_5&quot;,se=&quot;5&quot;,ss=&quot;2&quot;,p1=&quot;g&quot;"><Label><Emphasis style="italic">g</Emphasis>)</Label><Text>les avis juridiques rédigés pour le gouvernement du Canada.</Text></Paragraph></Subsection></Section></Group1-Part><Group1-Part Code="sc=&quot;&quot;,nb=&quot;1&quot;,ga=&quot;s_6&quot;"><Heading Code="sc=&quot;&quot;,nb=&quot;1&quot;,ga=&quot;s_6&quot;,h1=&quot;&quot;"><TitleText Code="sc=&quot;&quot;,nb=&quot;1&quot;,ga=&quot;s_6&quot;,h1=&quot;&quot;,t1=&quot;&quot;,nb=&quot;6&quot;">DEMANDE D’EXAMEN</TitleText></Heading><Section Code="sc=&quot;&quot;,nb=&quot;1&quot;,ga=&quot;s_6&quot;,se=&quot;6&quot;"><Label>6.</Label><Subsection Code="sc=&quot;&quot;,nb=&quot;1&quot;,ga=&quot;s_6&quot;,se=&quot;6&quot;,ss=&quot;1&quot;"><Label>(1)</Label><Text>L’ombudsman procède à l’examen de toute question qui relève de son mandat à la demande du ministre de la Justice ou du ministre de la Sécurité publique et de la Protection civile.</Text></Subsection><Subsection Code="sc=&quot;&quot;,nb=&quot;1&quot;,ga=&quot;s_6&quot;,se=&quot;6&quot;,ss=&quot;2&quot;"><Label>(2)</Label><Text>Il peut aussi procéder à un tel examen de sa propre initiative ou sur réception de toute demande d’examen provenant :</Text><Paragraph Code="sc=&quot;&quot;,nb=&quot;1&quot;,ga=&quot;s_6&quot;,se=&quot;6&quot;,ss=&quot;2&quot;,p1=&quot;a&quot;"><Label><Emphasis style="italic">a</Emphasis>)</Label><Text>d’une victime inscrite sous le régime de la <XRefExternal reference-type="act" link="C-44.6">Loi sur le système correctionnel et la mise en liberté sous condition</XRefExternal>, à l’égard de toute question relative aux droits des victimes prévus par cette loi;</Text></Paragraph><Paragraph Code="sc=&quot;&quot;,nb=&quot;1&quot;,ga=&quot;s_6&quot;,se=&quot;6&quot;,ss=&quot;2&quot;,p1=&quot;b&quot;"><Label><Emphasis style="italic">b</Emphasis>)</Label><Text>de toute autre victime, toute organisation de services aux victimes ou tout défenseur des droits des victimes, relativement à d’autres questions de compétence fédérale.</Text></Paragraph></Subsection><Subsection Code="sc=&quot;&quot;,nb=&quot;1&quot;,ga=&quot;s_6&quot;,se=&quot;6&quot;,ss=&quot;3&quot;"><Label>(3)</Label><Text>L’ombudsman peut :</Text><Paragraph Code="sc=&quot;&quot;,nb=&quot;1&quot;,ga=&quot;s_6&quot;,se=&quot;6&quot;,ss=&quot;3&quot;,p1=&quot;a&quot;"><Label><Emphasis style="italic">a</Emphasis>)</Label><Text>refuser de traiter toute demande d’examen, sauf celles reçues par le ministre de la Justice ou le ministre de la Sécurité publique et de la Protection civile;</Text></Paragraph><Paragraph Code="sc=&quot;&quot;,nb=&quot;1&quot;,ga=&quot;s_6&quot;,se=&quot;6&quot;,ss=&quot;3&quot;,p1=&quot;b&quot;"><Label><Emphasis style="italic">b</Emphasis>)</Label><Text>choisir les modalités de l’examen;</Text></Paragraph><Paragraph Code="sc=&quot;&quot;,nb=&quot;1&quot;,ga=&quot;s_6&quot;,se=&quot;6&quot;,ss=&quot;3&quot;,p1=&quot;c&quot;"><Label><Emphasis style="italic">c</Emphasis>)</Label><Text>décider s’il convient de cesser l’examen en cours de route.</Text></Paragraph></Subsection><Subsection Code="sc=&quot;&quot;,nb=&quot;1&quot;,ga=&quot;s_6&quot;,se=&quot;6&quot;,ss=&quot;4&quot;"><Label>(4)</Label><Text>Dans l’exercice de son pouvoir discrétionnaire prévu au paragraphe (3), l’ombudsman doit tenir compte :</Text><Paragraph Code="sc=&quot;&quot;,nb=&quot;1&quot;,ga=&quot;s_6&quot;,se=&quot;6&quot;,ss=&quot;4&quot;,p1=&quot;a&quot;"><Label><Emphasis style="italic">a</Emphasis>)</Label><Text>de la date à laquelle la demande a été présentée ou les faits sont survenus;</Text></Paragraph><Paragraph Code="sc=&quot;&quot;,nb=&quot;1&quot;,ga=&quot;s_6&quot;,se=&quot;6&quot;,ss=&quot;4&quot;,p1=&quot;b&quot;"><Label><Emphasis style="italic">b</Emphasis>)</Label><Text>du temps écoulé depuis que le demandeur a eu connaissance des faits;</Text></Paragraph><Paragraph Code="sc=&quot;&quot;,nb=&quot;1&quot;,ga=&quot;s_6&quot;,se=&quot;6&quot;,ss=&quot;4&quot;,p1=&quot;c&quot;"><Label><Emphasis style="italic">c</Emphasis>)</Label><Text>de la nature et de la gravité des faits;</Text></Paragraph><Paragraph Code="sc=&quot;&quot;,nb=&quot;1&quot;,ga=&quot;s_6&quot;,se=&quot;6&quot;,ss=&quot;4&quot;,p1=&quot;d&quot;"><Label><Emphasis style="italic">d</Emphasis>)</Label><Text>de la mesure dans laquelle les recours offerts pour obtenir réparation, le cas échéant, ont été épuisés.</Text></Paragraph></Subsection><Subsection Code="sc=&quot;&quot;,nb=&quot;1&quot;,ga=&quot;s_6&quot;,se=&quot;6&quot;,ss=&quot;5&quot;"><Label>(5)</Label><Text>À la date et selon le mode qu’il choisit, l’ombudsman informe le demandeur du résultat de l’examen ou des mesures prises pour donner suite à sa demande.</Text></Subsection></Section></Group1-Part><Group1-Part Code="sc=&quot;&quot;,nb=&quot;1&quot;,ga=&quot;s_7&quot;"><Heading Code="sc=&quot;&quot;,nb=&quot;1&quot;,ga=&quot;s_7&quot;,h1=&quot;&quot;"><TitleText Code="sc=&quot;&quot;,nb=&quot;1&quot;,ga=&quot;s_7&quot;,h1=&quot;&quot;,t1=&quot;&quot;,nb=&quot;7&quot;">REDDITION DE COMPTE ET RAPPORT ANNUEL</TitleText></Heading><Section Code="sc=&quot;&quot;,nb=&quot;1&quot;,ga=&quot;s_7&quot;,se=&quot;7&quot;"><Label>7.</Label><Subsection Code="sc=&quot;&quot;,nb=&quot;1&quot;,ga=&quot;s_7&quot;,se=&quot;7&quot;,ss=&quot;1&quot;"><Label>(1)</Label><Text>L’ombudsman doit rend compte au ministre de la Justice et relève directement de lui.</Text></Subsection><Subsection Code="sc=&quot;&quot;,nb=&quot;1&quot;,ga=&quot;s_7&quot;,se=&quot;7&quot;,ss=&quot;2&quot;"><Label>(2)</Label><Text>Il présente un rapport annuel des activités de son Bureau au ministre de la Justice, et ce dernier le dépose devant le Parlement.</Text></Subsection><Subsection Code="sc=&quot;&quot;,nb=&quot;1&quot;,ga=&quot;s_7&quot;,se=&quot;7&quot;,ss=&quot;3&quot;"><Label>(3)</Label><Text>Il peut publier le rapport dès le dépôt de celui-ci devant le Parlement.</Text></Subsection><Subsection Code="sc=&quot;&quot;,nb=&quot;1&quot;,ga=&quot;s_7&quot;,se=&quot;7&quot;,ss=&quot;4&quot;"><Label>(4)</Label><Text>Lorsque l’ombudsman estime que les renseignements contenus dans le rapport annuel risquent d’avoir une incidence négative sur toute personne ou organisation, il lui donne la possibilité de se faire entendre et il inclut un résumé fidèle de ses observations dans le rapport annuel. S’agissant de renseignements personnels, l’ombudsman doit se conformer aux dispositions applicables de la <XRefExternal reference-type="act" link="P-21">Loi sur la protection des renseignements personnels</XRefExternal>, de la <XRefExternal reference-type="act" link="A-1">Loi sur l’accès à l’information</XRefExternal> et de toute autre loi fédérale applicable.</Text></Subsection></Section></Group1-Part><Group1-Part Code="sc=&quot;&quot;,nb=&quot;1&quot;,ga=&quot;s_8&quot;"><Heading Code="sc=&quot;&quot;,nb=&quot;1&quot;,ga=&quot;s_8&quot;,h1=&quot;&quot;"><TitleText Code="sc=&quot;&quot;,nb=&quot;1&quot;,ga=&quot;s_8&quot;,h1=&quot;&quot;,t1=&quot;&quot;,nb=&quot;8&quot;">CONFIDENTIALITÉ</TitleText></Heading><Section Code="sc=&quot;&quot;,nb=&quot;1&quot;,ga=&quot;s_8&quot;,se=&quot;8&quot;"><Label>8.</Label><Text>L’ombudsman et les personnes agissant en son nom ne peuvent communiquer de renseignements qu’ils ont obtenus dans le cadre de leurs responsabilités sans le consentement des personnes visées, si ce n’est en conformité avec les lois fédérales.</Text></Section></Group1-Part><Group1-Part Code="sc=&quot;&quot;,nb=&quot;1&quot;,ga=&quot;s_9&quot;"><Heading Code="sc=&quot;&quot;,nb=&quot;1&quot;,ga=&quot;s_9&quot;,h1=&quot;&quot;"><TitleText Code="sc=&quot;&quot;,nb=&quot;1&quot;,ga=&quot;s_9&quot;,h1=&quot;&quot;,t1=&quot;&quot;,nb=&quot;9&quot;">AUTRES RAPPORTS ET RECOMMANDATIONS</TitleText></Heading><Section Code="sc=&quot;&quot;,nb=&quot;1&quot;,ga=&quot;s_9&quot;,se=&quot;9&quot;"><Label>9.</Label><Subsection Code="sc=&quot;&quot;,nb=&quot;1&quot;,ga=&quot;s_9&quot;,se=&quot;9&quot;,ss=&quot;1&quot;"><Label>(1)</Label><Text>L’ombudsman peut produire des rapports, avec ou sans recommandations, en tout temps, à l’égard de tout examen ou de toute autre question qui relève de son mandat. Les recommandations peuvent être faites au ministre de la Justice ouau ministre de la Sécurité publique et de la Protection civile ou aux deux, au besoin.</Text></Subsection><Subsection Code="sc=&quot;&quot;,nb=&quot;1&quot;,ga=&quot;s_9&quot;,se=&quot;9&quot;,ss=&quot;2&quot;"><Label>(2)</Label><Text>L’ombudsman doit tenter de régler toutes questions qui relèvent de son mandat au niveau où elles peuvent l’être réglés le plus efficacement possible et, à cette fins, il doit communiquer avec les fonctionnaires designés par le ministère de la Justice ou le ministère de la Sécurité publique et de la Protection civile, selon le cas.</Text></Subsection><Subsection Code="sc=&quot;&quot;,nb=&quot;1&quot;,ga=&quot;s_9&quot;,se=&quot;9&quot;,ss=&quot;3&quot;"><Label>(3)</Label><Text>Les recommandations de l’ombudsman ne sont pas contraignantes.</Text></Subsection><Subsection Code="sc=&quot;&quot;,nb=&quot;1&quot;,ga=&quot;s_9&quot;,se=&quot;9&quot;,ss=&quot;4&quot;"><Label>(4)</Label><Text>L’ombudsman peut demander à la direction du ministère de la Justice ou du ministère de la Sécurité publique et de la Protection civile, selon le cas, une réponse indiquant les mesures prises ou envisagées par suite de ses recommandations ou les raisons pour lesquelles telle mesure recommandée ne sera pas prise. Si la réponse de la direction est considérée comme inacceptable ou n’est pas reçue dans un délai raisonnable, l’ombudsman peut présenter le rapport au ministre de la Justice ou au ministre de la Sécurité publique et de la Protection civile, selon le cas.</Text></Subsection><Subsection Code="sc=&quot;&quot;,nb=&quot;1&quot;,ga=&quot;s_9&quot;,se=&quot;9&quot;,ss=&quot;5&quot;"><Label>(5)</Label><Text>L’ombudsman peut publier tout rapport, autre que le rapport annuel, à l’expiration d’une période de soixante jours suivant sa présentation au ministre de la Justice ou au ministre de la Sécurité publique et de la Protection civile, selon le cas.</Text></Subsection><Subsection Code="sc=&quot;&quot;,nb=&quot;1&quot;,ga=&quot;s_9&quot;,se=&quot;9&quot;,ss=&quot;6&quot;"><Label>(6)</Label><Text>Lorsque l’ombudsman estime que les renseignements contenus dans le rapport risquent d’avoir une incidence négative sur toute personne ou organisation, il lui donne la possibilité de se faire entendre et il inclut un résumé fidèle de ses observations dans le rapport. S’agissant de renseignements personnels, l’ombudsman doit se conformer aux dispositions applicables de la <XRefExternal reference-type="act">Loi sur la protection des renseignements personnels,</XRefExternal> de la <XRefExternal reference-type="act" link="A-1">Loi sur l’accès à l’information</XRefExternal> et de toute autre loi fédérale applicable.</Text></Subsection></Section></Group1-Part></Body></RegulationPiece></Schedule></Regulation>